glyphs_info_mcp/__init__.py
glyphs_info_mcp/__main__.py
glyphs_info_mcp/config.py
glyphs_info_mcp/modules_config.yaml
glyphs_info_mcp/server.py
glyphs_info_mcp/unified_tools.py
glyphs_info_mcp/data/class_hierarchy.py
glyphs_info_mcp/data/handbook-cache/stable/.cache-info.json
glyphs_info_mcp/data/handbook-cache/stable/anchors.md
glyphs_info_mcp/data/handbook-cache/stable/annotation-tool.md
glyphs_info_mcp/data/handbook-cache/stable/appendix.md
glyphs_info_mcp/data/handbook-cache/stable/automatic-feature-generation.md
glyphs_info_mcp/data/handbook-cache/stable/background.md
glyphs_info_mcp/data/handbook-cache/stable/batch-processing.md
glyphs_info_mcp/data/handbook-cache/stable/color-fonts.md
glyphs_info_mcp/data/handbook-cache/stable/color-fonts_colr-cpal.md
glyphs_info_mcp/data/handbook-cache/stable/color-fonts_general.md
glyphs_info_mcp/data/handbook-cache/stable/color-fonts_layered.md
glyphs_info_mcp/data/handbook-cache/stable/color-fonts_sbix.md
glyphs_info_mcp/data/handbook-cache/stable/color-fonts_svg.md
glyphs_info_mcp/data/handbook-cache/stable/components.md
glyphs_info_mcp/data/handbook-cache/stable/components_brushes.md
glyphs_info_mcp/data/handbook-cache/stable/components_cap.md
glyphs_info_mcp/data/handbook-cache/stable/components_corner.md
glyphs_info_mcp/data/handbook-cache/stable/components_segment.md
glyphs_info_mcp/data/handbook-cache/stable/components_smart.md
glyphs_info_mcp/data/handbook-cache/stable/create.md
glyphs_info_mcp/data/handbook-cache/stable/custom-feature-code-snippets.md
glyphs_info_mcp/data/handbook-cache/stable/custom-parameter-descriptions.md
glyphs_info_mcp/data/handbook-cache/stable/drawing-paths.md
glyphs_info_mcp/data/handbook-cache/stable/edit-view.md
glyphs_info_mcp/data/handbook-cache/stable/edit-view_images.md
glyphs_info_mcp/data/handbook-cache/stable/editing-multiple-masters.md
glyphs_info_mcp/data/handbook-cache/stable/editing-paths.md
glyphs_info_mcp/data/handbook-cache/stable/entering-text.md
glyphs_info_mcp-1.3.1.dist-info/METADATA
glyphs_info_mcp-1.3.1.dist-info/WHEEL
glyphs_info_mcp-1.3.1.dist-info/entry_points.txt
glyphs_info_mcp-1.3.1.dist-info/licenses/LICENSE
glyphs_info_mcp-1.3.1.dist-info/RECORD
