Metadata-Version: 2.4
Name: glyphs-info-mcp
Version: 1.3.1
Summary: Unified MCP server for Glyphs handbook and API queries
Project-URL: Homepage, https://github.com/yintzuyuan/glyphs-info-mcp
Project-URL: Repository, https://github.com/yintzuyuan/glyphs-info-mcp
Project-URL: Issues, https://github.com/yintzuyuan/glyphs-info-mcp/issues
Author-email: TzuYuan Yin <yintzuyuan@erikyin.net>
License: MIT
License-File: LICENSE
Classifier: Development Status :: 5 - Production/Stable
Classifier: Intended Audience :: Developers
Classifier: License :: OSI Approved :: MIT License
Classifier: Programming Language :: Python :: 3
Classifier: Programming Language :: Python :: 3.10
Classifier: Programming Language :: Python :: 3.11
Classifier: Programming Language :: Python :: 3.12
Requires-Python: >=3.10
Requires-Dist: httpx[http2]>=0.28.0
Requires-Dist: markdown-it-py>=3.0.0
Requires-Dist: markdownify>=1.1.0
Requires-Dist: mcp[cli]>=1.9.0
Requires-Dist: pathlib2>=2.3.7; python_version < '3.9'
Requires-Dist: platformdirs>=4.0.0
Requires-Dist: pydantic-settings>=2.8.0
Requires-Dist: pydantic>=2.10.0
Requires-Dist: python-dotenv>=1.0.0
Requires-Dist: pyyaml>=6.0.0
Requires-Dist: readabilipy>=0.3.0
Requires-Dist: rich>=13.9.0
Requires-Dist: typer>=0.15.0
Requires-Dist: typing-extensions>=4.12.0
Provides-Extra: dev
Requires-Dist: black>=24.0.0; extra == 'dev'
Requires-Dist: mypy>=1.8.0; extra == 'dev'
Requires-Dist: pre-commit>=3.6.0; extra == 'dev'
Requires-Dist: pytest-asyncio>=0.23.0; extra == 'dev'
Requires-Dist: pytest-cov>=4.0.0; extra == 'dev'
Requires-Dist: pytest>=8.0.0; extra == 'dev'
Requires-Dist: ruff>=0.1.0; extra == 'dev'
Requires-Dist: types-beautifulsoup4>=4.12.0; extra == 'dev'
Requires-Dist: types-pyyaml>=6.0.0; extra == 'dev'
Provides-Extra: docs
Requires-Dist: mkdocs-material>=9.0.0; extra == 'docs'
Requires-Dist: mkdocs>=1.5.0; extra == 'docs'
Requires-Dist: mkdocstrings[python]>=0.24.0; extra == 'docs'
Provides-Extra: test
Requires-Dist: pytest-asyncio>=0.23.0; extra == 'test'
Requires-Dist: pytest-cov>=4.0.0; extra == 'test'
Requires-Dist: pytest-mock>=3.12.0; extra == 'test'
Requires-Dist: pytest>=8.0.0; extra == 'test'
